msm_has_base/__init__.py
msm_has_base/apdu.py
msm_has_base/bc_info.py
msm_has_base/bc_reader.py
msm_has_base/card_reader.py
msm_has_base/epp.py
msm_has_base/pboc.py
msm_has_base/pos.py
msm_has_base/pos_ccb.py
msm_has_base/tlv.py
msm_has_base/utils.py
msm_has_base-0.1.16.dist-info/METADATA
msm_has_base-0.1.16.dist-info/WHEEL
msm_has_base-0.1.16.dist-info/top_level.txt
msm_has_base-0.1.16.dist-info/RECORD
