Metadata-Version: 2.1
Name: msm-has-base
Version: 0.1.16
Summary: Hardware Access Services Base Foundation
Author-email: 袁首京 <yuanshoujing@gmail.com>
Requires-Python: >=3.7
Requires-Dist: loguru
Requires-Dist: pyserial
Requires-Dist: requests
Provides-Extra: dev
Requires-Dist: pytest ; extra == 'dev'
Requires-Dist: build ; extra == 'dev'
Requires-Dist: twine ; extra == 'dev'
Requires-Dist: black ; extra == 'dev'
